Metadata-Version: 2.1
Name: norskfaktura
Version: 0.2.0
Summary: Norwegian database solution for invoicing in a small business
Home-page: UNKNOWN
Author: Svein-Kåre Bjørnsen
Author-email: bjornsenit@gmail.com
License: GPL-3.0-only
Platform: UNKNOWN
License-File: LICENSE
